pyextremes/__init__.py
pyextremes/eva.py
pyextremes/extremes/__init__.py
pyextremes/extremes/block_maxima.py
pyextremes/extremes/extremes.py
pyextremes/extremes/peaks_over_threshold.py
pyextremes/extremes/return_periods.py
pyextremes/extremes/transformation.py
pyextremes/models/__init__.py
pyextremes/models/distribution.py
pyextremes/models/model_base.py
pyextremes/models/model_emcee.py
pyextremes/models/model_lmoments.py
pyextremes/models/model_mle.py
pyextremes/models/model_mom.py
pyextremes/models/model_scipy.py
pyextremes/models/models.py
pyextremes/multivariate/__init__.py
pyextremes/multivariate/meva.py
pyextremes/plotting/__init__.py
pyextremes/plotting/extremes.py
pyextremes/plotting/mcmc.py
pyextremes/plotting/probability_plots.py
pyextremes/plotting/return_values.py
pyextremes/plotting/style.py
pyextremes/py.typed
pyextremes/tests/__init__.py
pyextremes/tests/ks_test.py
pyextremes/tests/test_base.py
pyextremes/tuning/__init__.py
pyextremes/tuning/hyperparameters.py
pyextremes/tuning/model_comparison.py
pyextremes/tuning/threshold_selection.py
pyextremes-2.4.0.dist-info/licenses/LICENSE
pyextremes-2.4.0.dist-info/WHEEL
pyextremes-2.4.0.dist-info/METADATA
pyextremes-2.4.0.dist-info/RECORD
