Metadata-Version: 2.4
Name: pyextremes
Version: 2.4.0
Summary: Extreme Value Analysis (EVA) in Python
Keywords: statistics,extreme,extreme value analysis,eva,coastal,ocean,oceanography,marine,environmental,engineering
Author: George Bocharov
Author-email: George Bocharov <bocharovgeorgii@gmail.com>
License-Expression: MIT
License-File: LICENSE
Classifier: Development Status :: 5 - Production/Stable
Classifier: Intended Audience :: Science/Research
Classifier: Intended Audience :: Developers
Classifier: License :: OSI Approved :: MIT License
Classifier: Operating System :: OS Independent
Classifier: Programming Language :: Python
Classifier: Programming Language :: Python :: 3
Classifier: Programming Language :: Python :: 3 :: Only
Classifier: Programming Language :: Python :: 3.9
Classifier: Programming Language :: Python :: 3.10
Classifier: Programming Language :: Python :: 3.11
Classifier: Programming Language :: Python :: 3.12
Classifier: Programming Language :: Python :: 3.13
Classifier: Topic :: Scientific/Engineering
Classifier: Topic :: Scientific/Engineering :: Hydrology
Classifier: Topic :: Scientific/Engineering :: Mathematics
Classifier: Typing :: Typed
Requires-Dist: numpy>=1.19.0,<3.0.0
Requires-Dist: scipy>=1.5.0,<2.0.0
Requires-Dist: pandas>=1.0.0,<3.0.0
Requires-Dist: emcee>=3.0.3,<4.0.0
Requires-Dist: matplotlib>=3.3.0,!=3.9.1,<4.0.0
Requires-Dist: lmoments3>=1.0.8 ; extra == 'full'
Requires-Dist: tqdm>=4.0.0,<5.0.0 ; extra == 'full'
Requires-Dist: lmoments3>=1.0.8 ; extra == 'lmoments'
Requires-Python: >=3.9
Project-URL: github, https://github.com/georgebv/pyextremes
Project-URL: homepage, https://georgebv.github.io/pyextremes
Provides-Extra: full
Provides-Extra: lmoments
